nanotracking/DifferencePlotter.py
nanotracking/DrawTable.py
nanotracking/InfoComparison.py
nanotracking/SetUpFolders.py
nanotracking/UI (deprecated).py
nanotracking/__init__.py
nanotracking/data_handler.c
nanotracking/data_handler.cpython-310-darwin.so
nanotracking/sample_class.py
nanotracking/settings_classes.py
nanotracking-0.0.6.dist-info/LICENSE
nanotracking-0.0.6.dist-info/METADATA
nanotracking-0.0.6.dist-info/WHEEL
nanotracking-0.0.6.dist-info/top_level.txt
nanotracking-0.0.6.dist-info/RECORD
