Metadata-Version: 2.1
Name: nanotracking
Version: 0.0.6
Summary: Provides visualization and analysis features for nanoparticle tracking analysis (NTA) data, particularly from the Horiba ViewSizer 3000.
Author-email: Henry Ingels <henryingels@gmail.com>
Project-URL: Homepage, https://github.com/hingels/SizeViewer
Project-URL: Issues, https://github.com/hingels/SizeViewer/issues
Classifier: Programming Language :: Python :: 3
Classifier: License :: OSI Approved :: MIT License
Classifier: Operating System :: OS Independent
Requires-Python: >=3.10
License-File: LICENSE
Requires-Dist: numpy
Requires-Dist: matplotlib
Requires-Dist: bottle
Requires-Dist: pandas
Requires-Dist: scipy
